jsonpython/__init__.py
jsonpython/json.py
jsonpython/json_core.py
jsonpython/parser.py
jsonpython-0.0.5.dist-info/LICENSE
jsonpython-0.0.5.dist-info/METADATA
jsonpython-0.0.5.dist-info/WHEEL
jsonpython-0.0.5.dist-info/top_level.txt
jsonpython-0.0.5.dist-info/RECORD
