Metadata-Version: 2.1
Name: jsonpython
Version: 0.0.5
Summary: A package to deserialize and serialize json files.
Home-page: https://github.com/TAFH-debug/jsonpy
Author: TAFH-debug
Author-email: aushahman2007@gmail.com
License: LICENSE
Classifier: Programming Language :: Python :: 3
Classifier: License :: OSI Approved :: MIT License
Classifier: Operating System :: OS Independent
License-File: LICENSE
